{"createdDate":"2020-07-29 18:02:49","id":"09632763-3261-47E7-996F-3C1E02528B99","modifiedDate":"2020-07-29 18:03:06","title":"Training Data","dataResult":{"itemsCount":75,"columns":["accelerometerAccelerationX","accelerometerAccelerationY","accelerometerAccelerationZ","accelerometerTimestamp_sinceReboot","gyroRotationX","gyroRotationY","gyroRotationZ","gyroTimestamp_sinceReboot","identifierForVendor","loggingSample","loggingTime"],"dataURL":"file:\/\/\/Users\/namita\/Desktop\/Updated%20Softball%20Swing%20Data%202\/Training%20Data\/","columnTypes":["Double","Double","Double","Double","Double","Double","Double","Double","Int","Int","Double"],"classesCount":5,"analysis":{"summary":{"canUseValidation":0,"classCount":5,"sampleCount":75},"issues":[{"description":"5 classes found, including Little Pivot, Good Swing, Pick Up Back Leg","severity":"info"},{"description":"Less than 100 total activity recording files found - add more to improve model validation","severity":"warning"},{"description":"Smallest class is \"Wild Pivot\" with 15 activity recording files","severity":"warning"},{"description":"Largest class is \"Little Pivot\" with 15 activity recording files","severity":"info"},{"description":"6 feature columns are selected","severity":"good"}],"classifierAnalysis":{"columns":[],"vizualizerSpec":"","labelStats":{"Pick Up Back Leg":15,"Good Swing":15,"Wild Pivot":15,"Little Pivot":15,"No Activity":15}}},"columnValues":["-0.34, -0.40, -0.38, -0.37, -0.35…","-0.83, -0.87, -0.88, -0.89, -0.88…","-0.25, -0.24, -0.33, -0.36, -0.32…","462,086.75, 462,086.78, 462,086.81, 462,086.84, 462,086.87…","-0.05, -0.01, -0.02, -0.00, 0.02…","0.07, 0.03, 0.09, -0.12, -0.09…","-0.12, -0.05, -0.08, -0.12, -0.07…","462,086.74, 462,086.77, 462,086.80, 462,086.83, 462,086.86…","0, 0, 0, 0, 0…","1, 2, 3, 4, 5…","1,595,776,423.39, 1,595,776,423.41, 1,595,776,423.45, 1,595,776,423.47, 1,595,776,423.52…"],"error":{"code":1000,"reason":"No feature columns selected","domain":"composer.error.domain","errorType":"notReady"}},"preferredFilename":"Training Data","version":"1.0","pathType":0,"experimentIDs":["62B11478-ECB0-494E-9300-4CEDD98BB538"]}